BohSME/output/vhdl/Creater.vhdl
library IEEE;
use IEEE.STD_LOGIC_1164.ALL;
use IEEE.NUMERIC_STD.ALL;

-- library SYSTEM_TYPES;
use work.SYSTEM_TYPES.ALL;

-- library CUSTOM_TYPES;
use work.CUSTOM_TYPES.ALL;


-- User defined packages here
-- #### USER-DATA-IMPORTS-START
-- #### USER-DATA-IMPORTS-END


entity Creater is
    generic(
        reset_a: in T_SYSTEM_INT32;
        reset_len: in T_SYSTEM_INT32;
        reset_data: in Creater_data_type
    );
    port(

        -- Output bus a1 signals
        a1_val: out T_SYSTEM_INT32;


        -- Clock signal
        CLK : in Std_logic;

        -- Ready signal
        RDY : in Std_logic;

        -- Finished signal
        FIN : out Std_logic;

        -- Enable signal
        ENB : in Std_logic;

        -- Reset signal
        RST : in Std_logic
    );
end Creater;

architecture RTL of Creater is




      -- User defined signals, procedures and components here
      -- #### USER-DATA-SIGNALS-START
      -- #### USER-DATA-SIGNALS-END

begin

    -- Custom processes go here
    -- #### USER-DATA-PROCESSES-START
    -- #### USER-DATA-PROCESSES-END




    process(
        -- Custom sensitivity signals here
        -- #### USER-DATA-SENSITIVITY-START
        -- #### USER-DATA-SENSITIVITY-END
        CLK,
        RST
    )
    -- Internal variables
    variable a : T_SYSTEM_INT32 := reset_a;
    variable len : T_SYSTEM_INT32 := reset_len;
    variable data : Creater_data_type := reset_data;


    -- #### USER-DATA-NONCLOCKEDVARIABLES-START
    -- #### USER-DATA-NONCLOCKEDVARIABLES-END
	begin
        -- Initialize code here
        -- #### USER-DATA-NONCLOCKEDSHAREDINITIALIZECODE-START
        -- #### USER-DATA-NONCLOCKEDSHAREDINITIALIZECODE-END

        if RST = '1' then
            a1_val <= TO_SIGNED(0, 32);
            a := reset_a;
            len := reset_len;
            data := reset_data;

                                    
            FIN <= '0';

            -- Initialize code here
            -- #### USER-DATA-NONCLOCKEDRESETCODE-START
            -- #### USER-DATA-NONCLOCKEDRESETCODE-END

        elsif rising_edge(CLK) then

            -- Initialize code here
            -- #### USER-DATA-NONCLOCKEDINITIALIZECODE-START
            -- #### USER-DATA-NONCLOCKEDINITIALIZECODE-END


            if a < len then
                a1_val <= data(TO_INTEGER(a));
                a := a + TO_SIGNED(1, 32);
            end if;



            FIN <= CLK;

        end if;

        -- Non-clocked process actions here

        -- #### USER-DATA-CODE-START
        -- #### USER-DATA-CODE-END

    end process;


end RTL;

-- User defined architectures here
-- #### USER-DATA-ARCH-START
-- #### USER-DATA-ARCH-END

BohSME/output/vhdl-backup-20191120T143620/instr1.vhdl
library IEEE;
use IEEE.STD_LOGIC_1164.ALL;
use IEEE.NUMERIC_STD.ALL;

-- library SYSTEM_TYPES;
use work.SYSTEM_TYPES.ALL;

-- library CUSTOM_TYPES;
use work.CUSTOM_TYPES.ALL;


-- User defined packages here
-- #### USER-DATA-IMPORTS-START
-- #### USER-DATA-IMPORTS-END


entity instr1 is
    port(
        -- Input bus a0 signals
        a0_val: in T_SYSTEM_INT32;

        -- Output bus a2 signals
        a2_val: out T_SYSTEM_INT32;


        -- Clock signal
        CLK : in Std_logic;

        -- Ready signal
        RDY : in Std_logic;

        -- Finished signal
        FIN : out Std_logic;

        -- Enable signal
        ENB : in Std_logic;

        -- Reset signal
        RST : in Std_logic
    );
end instr1;

architecture RTL of instr1 is




      -- User defined signals, procedures and components here
      -- #### USER-DATA-SIGNALS-START
      -- #### USER-DATA-SIGNALS-END

begin

    -- Custom processes go here
    -- #### USER-DATA-PROCESSES-START
    -- #### USER-DATA-PROCESSES-END




    process(
        -- Custom sensitivity signals here
        -- #### USER-DATA-SENSITIVITY-START
        -- #### USER-DATA-SENSITIVITY-END
        CLK,
        RST
    )


    -- #### USER-DATA-NONCLOCKEDVARIABLES-START
    -- #### USER-DATA-NONCLOCKEDVARIABLES-END
	begin
        -- Initialize code here
        -- #### USER-DATA-NONCLOCKEDSHAREDINITIALIZECODE-START
        -- #### USER-DATA-NONCLOCKEDSHAREDINITIALIZECODE-END

        if RST = '1' then
            a2_val <= TO_SIGNED(0, 32);

                                    
            FIN <= '0';

            -- Initialize code here
            -- #### USER-DATA-NONCLOCKEDRESETCODE-START
            -- #### USER-DATA-NONCLOCKEDRESETCODE-END

        elsif rising_edge(CLK) then

            -- Initialize code here
            -- #### USER-DATA-NONCLOCKEDINITIALIZECODE-START
            -- #### USER-DATA-NONCLOCKEDINITIALIZECODE-END


            a2_val <= a0_val + TO_SIGNED(2, 32);



            FIN <= CLK;

        end if;

        -- Non-clocked process actions here

        -- #### USER-DATA-CODE-START
        -- #### USER-DATA-CODE-END

    end process;


end RTL;

-- User defined architectures here
-- #### USER-DATA-ARCH-START
-- #### USER-DATA-ARCH-END

BohSME/output/vhdl-backup-20191120T141853/instr0.vhdl
library IEEE;
use IEEE.STD_LOGIC_1164.ALL;
use IEEE.NUMERIC_STD.ALL;

-- library SYSTEM_TYPES;
use work.SYSTEM_TYPES.ALL;

-- library CUSTOM_TYPES;
use work.CUSTOM_TYPES.ALL;


-- User defined packages here
-- #### USER-DATA-IMPORTS-START
-- #### USER-DATA-IMPORTS-END


entity instr0 is
    port(
        -- Input bus a1 signals
        a1_val: in T_SYSTEM_INT32;

        -- Output bus a0 signals
        a0_val: out T_SYSTEM_INT32;


        -- Clock signal
        CLK : in Std_logic;

        -- Ready signal
        RDY : in Std_logic;

        -- Finished signal
        FIN : out Std_logic;

        -- Enable signal
        ENB : in Std_logic;

        -- Reset signal
        RST : in Std_logic
    );
end instr0;

architecture RTL of instr0 is




      -- User defined signals, procedures and components here
      -- #### USER-DATA-SIGNALS-START
      -- #### USER-DATA-SIGNALS-END

begin

    -- Custom processes go here
    -- #### USER-DATA-PROCESSES-START
    -- #### USER-DATA-PROCESSES-END




    process(
        -- Custom sensitivity signals here
        -- #### USER-DATA-SENSITIVITY-START
        -- #### USER-DATA-SENSITIVITY-END
        CLK,
        RST
    )


    -- #### USER-DATA-NONCLOCKEDVARIABLES-START
    -- #### USER-DATA-NONCLOCKEDVARIABLES-END
	begin
        -- Initialize code here
        -- #### USER-DATA-NONCLOCKEDSHAREDINITIALIZECODE-START
        -- #### USER-DATA-NONCLOCKEDSHAREDINITIALIZECODE-END

        if RST = '1' then
            a0_val <= TO_SIGNED(0, 32);

                                    
            FIN <= '0';

            -- Initialize code here
            -- #### USER-DATA-NONCLOCKEDRESETCODE-START
            -- #### USER-DATA-NONCLOCKEDRESETCODE-END

        elsif rising_edge(CLK) then

            -- Initialize code here
            -- #### USER-DATA-NONCLOCKEDINITIALIZECODE-START
            -- #### USER-DATA-NONCLOCKEDINITIALIZECODE-END


            a0_val <= a1_val + a1_val;



            FIN <= CLK;

        end if;

        -- Non-clocked process actions here

        -- #### USER-DATA-CODE-START
        -- #### USER-DATA-CODE-END

    end process;


end RTL;

-- User defined architectures here
-- #### USER-DATA-ARCH-START
-- #### USER-DATA-ARCH-END

BohSME/output/vhdl/BohSME.vhdl
library IEEE;
use IEEE.STD_LOGIC_1164.ALL;
use IEEE.NUMERIC_STD.ALL;

-- library SYSTEM_TYPES;
use work.SYSTEM_TYPES.ALL;

-- library CUSTOM_TYPES;
use work.CUSTOM_TYPES.ALL;

-- User defined packages here
-- #### USER-DATA-IMPORTS-START
-- #### USER-DATA-IMPORTS-END

entity BohSME is
  port(


    -- Top-level bus tdata signals
    tdata_2_val: out T_SYSTEM_INT32;


    -- Interconnection bus tdata signals
    tdata_1_val: inout T_SYSTEM_INT32;
    -- Interconnection bus tdata signals
    tdata_0_val: inout T_SYSTEM_INT32;

    -- User defined signals here
    -- #### USER-DATA-ENTITYSIGNALS-START
    -- #### USER-DATA-ENTITYSIGNALS-END

    -- Enable signal
    ENB : in Std_logic;

    -- Finished signal
    FIN : out Std_logic;

	-- Reset signal
    RST : in Std_logic;

	-- Clock signal
	CLK : in Std_logic
  );
end BohSME;

architecture RTL of BohSME is  
    -- User defined signals here
    -- #### USER-DATA-SIGNALS-START
    -- #### USER-DATA-SIGNALS-END


    -- Process ready triggers

    signal FIN_instr0 : std_logic;

    signal FIN_instr1 : std_logic;

    signal FIN_Creater : std_logic;


    -- The primary ready driver signal
    signal RDY : std_logic;

begin


    -- Entity  instr0 signals
    instr0: entity work.instr0
    port map (
        -- Input bus tdata
        a1_val => tdata_1_val,


        -- Output bus tdata
        a0_val => tdata_0_val,



        CLK => CLK,
        RDY => RDY,
        FIN => FIN_instr0,
        ENB => ENB,
        RST => RST
    );


    -- Entity  instr1 signals
    instr1: entity work.instr1
    port map (
        -- Input bus tdata
        a0_val => tdata_0_val,


        -- Output bus tdata
        a2_val => tdata_2_val,



        CLK => CLK,
        RDY => RDY,
        FIN => FIN_instr1,
        ENB => ENB,
        RST => RST
    );


    -- Entity  Creater signals
    Creater: entity work.Creater
    generic map(
        reset_a => TO_SIGNED(0, 32),
        reset_len => TO_SIGNED(9, 32),
        reset_data => (TO_SIGNED(0, 32), TO_SIGNED(1, 32), TO_SIGNED(2, 32), TO_SIGNED(3, 32), TO_SIGNED(4, 32), TO_SIGNED(5, 32), TO_SIGNED(6, 32), TO_SIGNED(7, 32), others => TO_SIGNED(8, 32))
    )
    port map (
        -- Output bus tdata
        a1_val => tdata_1_val,



        CLK => CLK,
        RDY => RDY,
        FIN => FIN_Creater,
        ENB => ENB,
        RST => RST
    );


    -- Connect ready signals

    -- Setup the FIN feedback signals
    process(
      FIN_instr0, 
      FIN_instr1, 
      FIN_Creater
    )
    begin
      if FIN_instr0 = FIN_instr1 AND FIN_instr0 = FIN_Creater then
        FIN <= FIN_instr0;
      end if;
    end process;

    -- Propagate all clocked and feedback signals
    process(
        CLK,
        RST)

        variable readyflag: std_logic;
    begin
        if RST = '1' then
            RDY <= '0';
            readyflag := '1';
        elsif rising_edge(CLK) then
            if ENB = '1' then
                readyflag := not readyflag;
                RDY <= readyflag;


            end if;
        end if;
    end process;



-- User defined processes here
-- #### USER-DATA-CODE-START
-- #### USER-DATA-CODE-END

end RTL;

BohSME/output/vhdl/TestBench_BohSME.vhdl

library IEEE;
use IEEE.STD_LOGIC_1164.ALL;
use IEEE.NUMERIC_STD.ALL;
use STD.TEXTIO.all;
use IEEE.STD_LOGIC_TEXTIO.all;

--library SYSTEM_TYPES;
use work.SYSTEM_TYPES.ALL;

--library CUSTOM_TYPES;
use work.CUSTOM_TYPES.ALL;

use work.csv_util.all;

-- User defined packages here
-- #### USER-DATA-IMPORTS-START
-- #### USER-DATA-IMPORTS-END

entity BohSME_tb is
end;

architecture TestBench of BohSME_tb is

  signal CLOCK : Std_logic;
  signal StopClock : BOOLEAN;
  signal RESET : Std_logic;
  signal ENABLE : Std_logic;

  signal tdata_1_val : T_SYSTEM_INT32;
  signal tdata_0_val : T_SYSTEM_INT32;
  signal tdata_2_val : T_SYSTEM_INT32;

begin

  uut: entity work.BohSME
  port map (

    tdata_1_val => tdata_1_val,
    tdata_0_val => tdata_0_val,
    tdata_2_val => tdata_2_val,

    ENB => ENABLE,
    RST => RESET,
    CLK => CLOCK
  );

  Clk: process
  begin
    while not StopClock loop
      CLOCK <= '1';
      wait for 5 NS;
      CLOCK <= '0';
      wait for 5 NS;
    end loop;
    wait;
  end process;


TraceFileTester: process
    file F: TEXT;
    variable L: LINE;
    variable Status: FILE_OPEN_STATUS;
    constant filename : string := "./trace.csv";
    variable clockcycle : integer := 0;
    variable tmp : CSV_LINE_T;
    variable readOK : boolean;
    variable fieldno : integer := 0;
    variable failures : integer := 0;
    variable newfailures: integer := 0;
    variable first_failure_tick : integer := -1;
    variable first_round : boolean := true;

begin

    -- #### USER-DATA-CONDITONING-START
    -- #### USER-DATA-CONDITONING-END

    FILE_OPEN(Status, F, filename, READ_MODE);
    if Status /= OPEN_OK then
        report "Failed to open CSV trace file" severity Failure;
    else
        -- Verify the headers
        READLINE(F, L);

        fieldno := 0;
        read_csv_field(L, tmp);
        assert are_strings_equal(tmp, "tdata#0.val") report "Field #" & integer'image(fieldno) & " is not correctly named: " & truncate(tmp) & ", expected tdata#0.val" severity Failure;
        fieldno := fieldno + 1;
        read_csv_field(L, tmp);
        assert are_strings_equal(tmp, "tdata#1.val") report "Field #" & integer'image(fieldno) & " is not correctly named: " & truncate(tmp) & ", expected tdata#1.val" severity Failure;
        fieldno := fieldno + 1;
        read_csv_field(L, tmp);
        assert are_strings_equal(tmp, "tdata#2.val") report "Field #" & integer'image(fieldno) & " is not correctly named: " & truncate(tmp) & ", expected tdata#2.val" severity Failure;
        fieldno := fieldno + 1;

        RESET <= '1';
        ENABLE <= '0';
        wait for 5 NS;
        RESET <= '0';
        ENABLE <= '1';

        READLINE(F, L);
        -- Read a line each clock
        while not ENDFILE(F) loop
            READLINE(F, L);

            fieldno := 0;
            newfailures := 0;


            if first_round then
                wait until rising_edge(CLOCK);
                first_round := false;
            end if;

            -- Wait until the signals are settled before veriying the results
            wait until falling_edge(CLOCK);

            -- Compare each signal with the value in the CSV file
	        read_csv_field(L, tmp);
	        if not are_strings_equal(tmp, "U") then
            	if not are_strings_equal(str(tdata_0_val), tmp) then
                    newfailures := newfailures + 1;
                    report "Value for tdata_0_val in cycle " & integer'image(clockcycle) & " was: " & str(tdata_0_val) & " but should have been: " & truncate(tmp) severity Error;
                end if;
            end if;
            fieldno := fieldno + 1;

	        read_csv_field(L, tmp);
	        if not are_strings_equal(tmp, "U") then
            	if not are_strings_equal(str(tdata_1_val), tmp) then
                    newfailures := newfailures + 1;
                    report "Value for tdata_1_val in cycle " & integer'image(clockcycle) & " was: " & str(tdata_1_val) & " but should have been: " & truncate(tmp) severity Error;
                end if;
            end if;
            fieldno := fieldno + 1;

	        read_csv_field(L, tmp);
	        if not are_strings_equal(tmp, "U") then
            	if not are_strings_equal(str(tdata_2_val), tmp) then
                    newfailures := newfailures + 1;
                    report "Value for tdata_2_val in cycle " & integer'image(clockcycle) & " was: " & str(tdata_2_val) & " but should have been: " & truncate(tmp) severity Error;
                end if;
            end if;
            fieldno := fieldno + 1;

            failures := failures + newfailures;
            if newfailures = 0 then
                first_failure_tick := -1;
            elsif first_failure_tick = -1 then
                first_failure_tick := clockcycle;
            else
                if clockcycle - first_failure_tick >= 5 then
                    report "Stopping simulation due to five consecutive failed cycles" severity error;
                    StopClock <= true;
                elsif failures > 20 then
                    report "Stopping simulation after 20 failures" severity error;
                    StopClock <= true;
                end if;
            end if;

            clockcycle := clockcycle + 1;
        end loop;

        FILE_CLOSE(F);
    end if;

    if failures = 0 then
        report "completed successfully after " & integer'image(clockcycle) & " clockcycles";
    else
        report "completed with " & integer'image(failures) & " error(s) after " & integer'image(clockcycle) & " clockcycle(s)";
    end if;
    StopClock <= true;

    wait;
end process;
end architecture TestBench;

BohSME/output/vhdl/trace.vcd
$date
  Wed Nov 20 14:38:21 2019
$end
$version
  GHDL v0
$end
$timescale
  1 fs
$end
$scope module standard $end
$upscope $end
$scope module std_logic_1164 $end
$upscope $end
$scope module numeric_std $end
$upscope $end
$scope module textio $end
$upscope $end
$scope module std_logic_textio $end
$upscope $end
$scope module system_types $end
$upscope $end
$scope module custom_types $end
$upscope $end
$scope module csv_util $end
$upscope $end
$scope module bohsme_tb $end
$var reg 1 ! clock $end
$var reg 1 " stopclock $end
$var reg 1 # reset $end
$var reg 1 $ enable $end
$var reg 32 % tdata_1_val[31:0] $end
$var reg 32 & tdata_0_val[31:0] $end
$var reg 32 ' tdata_2_val[31:0] $end
$scope module uut $end
$var reg 32 ( tdata_2_val[31:0] $end
$var reg 32 ) tdata_1_val[31:0] $end
$var reg 32 * tdata_0_val[31:0] $end
$var reg 1 + enb $end
$var reg 1 , fin $end
$var reg 1 - rst $end
$var reg 1 . clk $end
$var reg 1 / fin_instr0 $end
$var reg 1 0 fin_instr1 $end
$var reg 1 1 fin_creater $end
$var reg 1 2 rdy $end
$scope module instr0 $end
$var reg 32 3 a1_val[31:0] $end
$var reg 32 4 a0_val[31:0] $end
$var reg 1 5 clk $end
$var reg 1 6 rdy $end
$var reg 1 7 fin $end
$var reg 1 8 enb $end
$var reg 1 9 rst $end
$upscope $end
$scope module instr1 $end
$var reg 32 : a0_val[31:0] $end
$var reg 32 ; a2_val[31:0] $end
$var reg 1 < clk $end
$var reg 1 = rdy $end
$var reg 1 > fin $end
$var reg 1 ? enb $end
$var reg 1 @ rst $end
$upscope $end
$scope module creater $end
$var reg 32 A a1_val[31:0] $end
$var reg 1 B clk $end
$var reg 1 C rdy $end
$var reg 1 D fin $end
$var reg 1 E enb $end
$var reg 1 F rst $end
$upscope $end
$upscope $end
$upscope $end
$enddefinitions $end
#0
1!
0"
1#
0$
b00000000000000000000000000000000 %
b00000000000000000000000000000000 &
b00000000000000000000000000000000 '
b00000000000000000000000000000000 (
b00000000000000000000000000000000 )
b00000000000000000000000000000000 *
0+
0,
1-
1.
0/
00
01
02
b00000000000000000000000000000000 3
b00000000000000000000000000000000 4
15
06
07
08
19
b00000000000000000000000000000000 :
b00000000000000000000000000000000 ;
1<
0=
0>
0?
1@
b00000000000000000000000000000000 A
1B
0C
0D
0E
1F
#5000000
0!
0#
1$
1+
0-
0.
05
18
09
0<
1?
0@
0B
1E
0F
#10000000
1!
b00000000000000000000000000000010 '
b00000000000000000000000000000010 (
1,
1.
1/
10
11
15
17
b00000000000000000000000000000010 ;
1<
1>
1B
1D
#15000000
0!
0.
05
0<
0B
#20000000
1!
b00000000000000000000000000000001 %
b00000000000000000000000000000001 )
1.
12
b00000000000000000000000000000001 3
15
16
1<
1=
b00000000000000000000000000000001 A
1B
1C
#25000000
0!
0.
05
0<
0B
#30000000
1!
b00000000000000000000000000000010 %
b00000000000000000000000000000010 &
b00000000000000000000000000000010 )
b00000000000000000000000000000010 *
1.
02
b00000000000000000000000000000010 3
b00000000000000000000000000000010 4
15
06
b00000000000000000000000000000010 :
1<
0=
b00000000000000000000000000000010 A
1B
0C
#35000000
0!
0.
05
0<
0B
#40000000
1!
b00000000000000000000000000000011 %
b00000000000000000000000000000100 &
b00000000000000000000000000000100 '
b00000000000000000000000000000100 (
b00000000000000000000000000000011 )
b00000000000000000000000000000100 *
1.
12
b00000000000000000000000000000011 3
b00000000000000000000000000000100 4
15
16
b00000000000000000000000000000100 :
b00000000000000000000000000000100 ;
1<
1=
b00000000000000000000000000000011 A
1B
1C
#45000000
0!
0.
05
0<
0B
#50000000
1!
b00000000000000000000000000000100 %
b00000000000000000000000000000110 &
b00000000000000000000000000000110 '
b00000000000000000000000000000110 (
b00000000000000000000000000000100 )
b00000000000000000000000000000110 *
1.
02
b00000000000000000000000000000100 3
b00000000000000000000000000000110 4
15
06
b00000000000000000000000000000110 :
b00000000000000000000000000000110 ;
1<
0=
b00000000000000000000000000000100 A
1B
0C
#55000000
0!
0.
05
0<
0B
#60000000
1!
b00000000000000000000000000000101 %
b00000000000000000000000000001000 &
b00000000000000000000000000001000 '
b00000000000000000000000000001000 (
b00000000000000000000000000000101 )
b00000000000000000000000000001000 *
1.
12
b00000000000000000000000000000101 3
b00000000000000000000000000001000 4
15
16
b00000000000000000000000000001000 :
b00000000000000000000000000001000 ;
1<
1=
b00000000000000000000000000000101 A
1B
1C
#65000000
0!
0.
05
0<
0B
#70000000
1!
b00000000000000000000000000000110 %
b00000000000000000000000000001010 &
b00000000000000000000000000001010 '
b00000000000000000000000000001010 (
b00000000000000000000000000000110 )
b00000000000000000000000000001010 *
1.
02
b00000000000000000000000000000110 3
b00000000000000000000000000001010 4
15
06
b00000000000000000000000000001010 :
b00000000000000000000000000001010 ;
1<
0=
b00000000000000000000000000000110 A
1B
0C
#75000000
0!
0.
05
0<
0B
#80000000
1!
b00000000000000000000000000000111 %
b00000000000000000000000000001100 &
b00000000000000000000000000001100 '
b00000000000000000000000000001100 (
b00000000000000000000000000000111 )
b00000000000000000000000000001100 *
1.
12
b00000000000000000000000000000111 3
b00000000000000000000000000001100 4
15
16
b00000000000000000000000000001100 :
b00000000000000000000000000001100 ;
1<
1=
b00000000000000000000000000000111 A
1B
1C
#85000000
0!
0.
05
0<
0B
#90000000
1!
b00000000000000000000000000001000 %
b00000000000000000000000000001110 &
b00000000000000000000000000001110 '
b00000000000000000000000000001110 (
b00000000000000000000000000001000 )
b00000000000000000000000000001110 *
1.
02
b00000000000000000000000000001000 3
b00000000000000000000000000001110 4
15
06
b00000000000000000000000000001110 :
b00000000000000000000000000001110 ;
1<
0=
b00000000000000000000000000001000 A
1B
0C
#95000000
0!
0.
05
0<
0B
#100000000
1!
b00000000000000000000000000010000 &
b00000000000000000000000000010000 '
b00000000000000000000000000010000 (
b00000000000000000000000000010000 *
1.
12
b00000000000000000000000000010000 4
15
16
b00000000000000000000000000010000 :
b00000000000000000000000000010000 ;
1<
1=
1B
1C
#105000000
0!
0.
05
0<
0B
#110000000
1!
b00000000000000000000000000010010 '
b00000000000000000000000000010010 (
1.
02
15
06
b00000000000000000000000000010010 ;
1<
0=
1B
0C
#115000000
0!
0.
05
0<
0B
#120000000
1!
1.
12
15
16
1<
1=
1B
1C
#125000000
0!
0.
05
0<
0B
#130000000
1!
1.
02
15
06
1<
0=
1B
0C
#135000000
0!
0.
05
0<
0B
#140000000
1!
1.
12
15
16
1<
1=
1B
1C
#145000000
0!
0.
05
0<
0B
#150000000
1!
1.
02
15
06
1<
0=
1B
0C
